[
  {
    "src": "/galeria1.webp",
    "alt": "Plato Gourmet 1"
  },
  {
    "src": "/galeria2.webp",
    "alt": "Nuestro Sal贸n",
    "className": "md:col-span-2 md:row-span-2"
  },
  {
    "src": "/galeria3.webp",
    "alt": "Chef en acci贸n"
  },
  {
    "src": "/galeria4.webp",
    "alt": "Cava de vinos"
  },
  {
    "src": "/galeria5.webp",
    "alt": "Detalle de mesa",
    "className": "md:col-span-2 md:row-span-2"
  },
  {
    "src": "/galeria6.webp",
    "alt": "Postre de autor"
  },
  {
    "src": "/galeria7.webp",
    "alt": "Vista nocturna del restaurante"
  },
  {
    "src": "/galeria8.webp",
    "alt": "Brindis con champagne",
    "className": "md:col-span-2 md:row-span-2"
  },
  {
    "src": "/galeria9.webp",
    "alt": "Entrada elegante"
  },
  {
    "src": "/galeria10.webp",
    "alt": "Chef preparando plato"
  },
  {
    "src": "/galeria11.webp",
    "alt": "Ambiente acogedor",
    "className": "md:col-span-2 md:row-span-2"
  },
  {
    "src": "/galeria12.webp",
    "alt": "Selecci贸n de vinos"
  },
  {
    "src": "/galeria13.webp",
    "alt": "Cocina abierta"
  },
  {
    "src": "/galeria14.webp",
    "alt": "Equipo de chefs",
    "className": "md:col-span-2 md:row-span-2"
  },
  {
    "src": "/galeria15.webp",
    "alt": "C贸cteles exclusivos"
  }
]